clicker/__init__.py
clicker/cli.py
clicker/main.py
clicker-0.2.5.dist-info/entry_points.txt
clicker-0.2.5.dist-info/LICENSE
clicker-0.2.5.dist-info/LICENSE.txt
clicker-0.2.5.dist-info/WHEEL
clicker-0.2.5.dist-info/METADATA
clicker-0.2.5.dist-info/RECORD
