Metadata-Version: 2.1
Name: clicker
Version: 0.2.5
Summary: clicker
Home-page: https://github.com/ryanwang520
License: UNKNOWN
Author: Ryan Wang
Author-email: hwwangwang@gmail.com
Classifier: License :: OSI Approved :: MIT License
